<annotation>
	<folder>JPEGImages</folder>
	<filename>1031.jpg</filename>
	<path>C:\Users\admin\Desktop\handpose_x_gesture_v3\JPEGImages\1031.jpg</path>
	<source>
		<database>Unknown</database>
	</source>
	<size>
		<width>101</width>
		<height>109</height>
		<depth>3</depth>
	</size>
	<segmented>0</segmented>
	<object>
		<name>up</name>
		<pose>Unspecified</pose>
		<truncated>0</truncated>
		<difficult>0</difficult>
		<bndbox>
			<xmin>27</xmin>
			<ymin>13</ymin>
			<xmax>76</xmax>
			<ymax>92</ymax>
		</bndbox>
	</object>
</annotation>
