<annotation>
	<folder>JPEGImages</folder>
	<filename>1270.jpg</filename>
	<path>C:\Users\admin\Desktop\handpose_x_gesture_v3\JPEGImages\1270.jpg</path>
	<source>
		<database>Unknown</database>
	</source>
	<size>
		<width>280</width>
		<height>273</height>
		<depth>3</depth>
	</size>
	<segmented>0</segmented>
	<object>
		<name>down</name>
		<pose>Unspecified</pose>
		<truncated>0</truncated>
		<difficult>0</difficult>
		<bndbox>
			<xmin>51</xmin>
			<ymin>60</ymin>
			<xmax>229</xmax>
			<ymax>214</ymax>
		</bndbox>
	</object>
</annotation>
