<annotation>
	<folder>JPEGImages</folder>
	<filename>223.jpg</filename>
	<path>E:\handpose_x_gesture_v2\JPEGImages\223.jpg</path>
	<source>
		<database>Unknown</database>
	</source>
	<size>
		<width>130</width>
		<height>141</height>
		<depth>3</depth>
	</size>
	<segmented>0</segmented>
	<object>
		<name>left</name>
		<pose>Unspecified</pose>
		<truncated>0</truncated>
		<difficult>0</difficult>
		<bndbox>
			<xmin>27</xmin>
			<ymin>19</ymin>
			<xmax>98</xmax>
			<ymax>103</ymax>
		</bndbox>
	</object>
</annotation>
