<annotation>
	<folder>JPEGImages</folder>
	<filename>568.jpg</filename>
	<path>E:\handpose_x_gesture_v2\JPEGImages\568.jpg</path>
	<source>
		<database>Unknown</database>
	</source>
	<size>
		<width>262</width>
		<height>318</height>
		<depth>3</depth>
	</size>
	<segmented>0</segmented>
	<object>
		<name>back</name>
		<pose>Unspecified</pose>
		<truncated>0</truncated>
		<difficult>0</difficult>
		<bndbox>
			<xmin>9</xmin>
			<ymin>16</ymin>
			<xmax>221</xmax>
			<ymax>250</ymax>
		</bndbox>
	</object>
</annotation>
