<annotation>
	<folder>JPEGImages</folder>
	<filename>849.jpg</filename>
	<path>E:\front2\JPEGImages\849.jpg</path>
	<source>
		<database>Unknown</database>
	</source>
	<size>
		<width>178</width>
		<height>202</height>
		<depth>3</depth>
	</size>
	<segmented>0</segmented>
	<object>
		<name>front</name>
		<pose>Unspecified</pose>
		<truncated>0</truncated>
		<difficult>0</difficult>
		<bndbox>
			<xmin>41</xmin>
			<ymin>10</ymin>
			<xmax>133</xmax>
			<ymax>177</ymax>
		</bndbox>
	</object>
</annotation>
